a5client/__init__.py
a5client/a5_client.py
a5client/a5_schemas.py
a5client/config.py
a5client/schemas.py
a5client/types.py
a5_client-0.1.15.dist-info/METADATA
a5_client-0.1.15.dist-info/WHEEL
a5_client-0.1.15.dist-info/top_level.txt
a5_client-0.1.15.dist-info/RECORD
