Metadata-Version: 2.4
Name: a5_client
Version: 0.1.15
Summary: a5 api client for python
Home-page: https://github.com/jbianchi81/a5_client
Author: Juan F. Bianchi
Author-email: SSIyAH-INA <jbianchi@ina.gob.ar>
License: MIT License
Project-URL: Homepage, http://github.com/jbianchi81/a5client
Classifier: Programming Language :: Python :: 3
Classifier: License :: OSI Approved :: MIT License
Classifier: Operating System :: OS Independent
Requires-Python: >=3.8
Requires-Dist: pandas
Requires-Dist: jsonschema
Requires-Dist: requests
Requires-Dist: datetime
Requires-Dist: pyyaml
Requires-Dist: a5_client_utils
Dynamic: author
Dynamic: home-page
